{
  "scope": "congressional",
  "contest_type": "secretary_of_state",
  "year": 2022,
  "state": "MN",
  "general": {
    "results": {
      "1": {
        "district": "1",
        "dem_votes": 135449,
        "rep_votes": 157548,
        "other_votes": 184,
        "total_votes": 293181,
        "dem_candidate": "Steve Simon",
        "rep_candidate": "Kim Crockett",
        "margin": 22099,
        "margin_pct": 7.537664,
        "winner": "REPUBLICAN",
        "color": "#fb6a4a"
      },
      "2": {
        "district": "2",
        "dem_votes": 171250,
        "rep_votes": 142536,
        "other_votes": 374,
        "total_votes": 314160,
        "dem_candidate": "Steve Simon",
        "rep_candidate": "Kim Crockett",
        "margin": -28714,
        "margin_pct": -9.139929,
        "winner": "DEMOCRAT",
        "color": "#9ecae1"
      },
      "3": {
        "district": "3",
        "dem_votes": 201915,
        "rep_votes": 128282,
        "other_votes": 239,
        "total_votes": 330436,
        "dem_candidate": "Steve Simon",
        "rep_candidate": "Kim Crockett",
        "margin": -73633,
        "margin_pct": -22.283589,
        "winner": "DEMOCRAT",
        "color": "#3182bd"
      },
      "4": {
        "district": "4",
        "dem_votes": 205439,
        "rep_votes": 88463,
        "other_votes": 321,
        "total_votes": 294223,
        "dem_candidate": "Steve Simon",
        "rep_candidate": "Kim Crockett",
        "margin": -116976,
        "margin_pct": -39.757599,
        "winner": "DEMOCRAT",
        "color": "#08519c"
      },
      "5": {
        "district": "5",
        "dem_votes": 241662,
        "rep_votes": 49020,
        "other_votes": 299,
        "total_votes": 290981,
        "dem_candidate": "Steve Simon",
        "rep_candidate": "Kim Crockett",
        "margin": -192642,
        "margin_pct": -66.204323,
        "winner": "DEMOCRAT",
        "color": "#08306b"
      },
      "6": {
        "district": "6",
        "dem_votes": 134223,
        "rep_votes": 181451,
        "other_votes": 235,
        "total_votes": 315909,
        "dem_candidate": "Steve Simon",
        "rep_candidate": "Kim Crockett",
        "margin": 47228,
        "margin_pct": 14.949875,
        "winner": "REPUBLICAN",
        "color": "#ef3b2c"
      },
      "7": {
        "district": "7",
        "dem_votes": 104581,
        "rep_votes": 198608,
        "other_votes": 227,
        "total_votes": 303416,
        "dem_candidate": "Steve Simon",
        "rep_candidate": "Kim Crockett",
        "margin": 94027,
        "margin_pct": 30.989467,
        "winner": "REPUBLICAN",
        "color": "#a50f15"
      },
      "8": {
        "district": "8",
        "dem_votes": 151167,
        "rep_votes": 174041,
        "other_votes": 215,
        "total_votes": 325423,
        "dem_candidate": "Steve Simon",
        "rep_candidate": "Kim Crockett",
        "margin": 22874,
        "margin_pct": 7.029005,
        "winner": "REPUBLICAN",
        "color": "#fb6a4a"
      }
    }
  },
  "meta": {
    "source_file": "20221108__mn__general__precinct.csv",
    "crosswalk_file": "precinct_to_cd118.csv",
    "generated_at_utc": "2026-03-22T20:53:06Z",
    "total_input_votes": 2467729,
    "crosswalk_matched_votes": 2152074,
    "fallback_matched_votes": 315655,
    "county_fallback_votes": 0,
    "unmatched_votes": 0,
    "match_coverage_pct": 100.0,
    "crosswalk_match_pct": 87.2087
  }
}
