{"scope":"state_senate","contest_type":"president","year":2016,"state":"MN","general":{"results":{"1":{"district":"1","dem_votes":13307,"rep_votes":26606,"other_votes":3434,"total_votes":43347,"dem_candidate":"Hillary Clinton and Tim Kaine","rep_candidate":"Donald J. Trump and Michael R. Pence","margin":13299,"margin_pct":30.680324,"winner":"REPUBLICAN","color":"#a50f15"},"2":{"district":"2","dem_votes":14954,"rep_votes":21956,"other_votes":3392,"total_votes":40302,"dem_candidate":"Hillary Clinton and Tim Kaine","rep_candidate":"Donald J. Trump and Michael R. Pence","margin":7002,"margin_pct":17.373828,"winner":"REPUBLICAN","color":"#ef3b2c"},"3":{"district":"3","dem_votes":23488,"rep_votes":24614,"other_votes":4198,"total_votes":52300,"dem_candidate":"Hillary Clinton and Tim Kaine","rep_candidate":"Donald J. Trump and Michael R. Pence","margin":1126,"margin_pct":2.152964,"winner":"REPUBLICAN","color":"#fcae91"},"4":{"district":"4","dem_votes":15560,"rep_votes":19068,"other_votes":3406,"total_votes":38034,"dem_candidate":"Hillary Clinton and Tim Kaine","rep_candidate":"Donald J. Trump and Michael R. Pence","margin":3508,"margin_pct":9.223326,"winner":"REPUBLICAN","color":"#fb6a4a"},"5":{"district":"5","dem_votes":10992,"rep_votes":29706,"other_votes":2759,"total_votes":43457,"dem_candidate":"Hillary Clinton and Tim Kaine","rep_candidate":"Donald J. Trump and Michael R. Pence","margin":18714,"margin_pct":43.063258,"winner":"REPUBLICAN","color":"#67000d"},"6":{"district":"6","dem_votes":14900,"rep_votes":27236,"other_votes":3367,"total_votes":45503,"dem_candidate":"Hillary Clinton and Tim Kaine","rep_candidate":"Donald J. Trump and Michael R. Pence","margin":12336,"margin_pct":27.1103,"winner":"REPUBLICAN","color":"#cb181d"},"7":{"district":"7","dem_votes":17511,"rep_votes":20244,"other_votes":3335,"total_votes":41090,"dem_candidate":"Hillary Clinton and Tim Kaine","rep_candidate":"Donald J. Trump and Michael R. Pence","margin":2733,"margin_pct":6.651253,"winner":"REPUBLICAN","color":"#fb6a4a"},"8":{"district":"8","dem_votes":29259,"rep_votes":15300,"other_votes":4910,"total_votes":49469,"dem_candidate":"Hillary Clinton and Tim Kaine","rep_candidate":"Donald J. Trump and Michael R. Pence","margin":-13959,"margin_pct":-28.217672,"winner":"DEMOCRAT","color":"#3182bd"},"9":{"district":"9","dem_votes":13356,"rep_votes":29533,"other_votes":3318,"total_votes":46207,"dem_candidate":"Hillary Clinton and Tim Kaine","rep_candidate":"Donald J. Trump and Michael R. Pence","margin":16177,"margin_pct":35.009847,"winner":"REPUBLICAN","color":"#a50f15"},"10":{"district":"10","dem_votes":11688,"rep_votes":32017,"other_votes":3032,"total_votes":46737,"dem_candidate":"Hillary Clinton and Tim Kaine","rep_candidate":"Donald J. Trump and Michael R. Pence","margin":20329,"margin_pct":43.496587,"winner":"REPUBLICAN","color":"#67000d"},"11":{"district":"11","dem_votes":16265,"rep_votes":22431,"other_votes":3467,"total_votes":42163,"dem_candidate":"Hillary Clinton and Tim Kaine","rep_candidate":"Donald J. Trump and Michael R. Pence","margin":6166,"margin_pct":14.624197,"winner":"REPUBLICAN","color":"#ef3b2c"},"12":{"district":"12","dem_votes":16820,"rep_votes":32594,"other_votes":3994,"total_votes":53408,"dem_candidate":"Hillary Clinton and Tim Kaine","rep_candidate":"Donald J. Trump and Michael R. Pence","margin":15774,"margin_pct":29.534901,"winner":"REPUBLICAN","color":"#cb181d"},"13":{"district":"13","dem_votes":18465,"rep_votes":35810,"other_votes":4691,"total_votes":58966,"dem_candidate":"Hillary Clinton and Tim Kaine","rep_candidate":"Donald J. Trump and Michael R. Pence","margin":17345,"margin_pct":29.415256,"winner":"REPUBLICAN","color":"#cb181d"},"14":{"district":"14","dem_votes":5599,"rep_votes":7815,"other_votes":1345,"total_votes":14759,"dem_candidate":"Hillary Clinton and Tim Kaine","rep_candidate":"Donald J. Trump and Michael R. Pence","margin":2216,"margin_pct":15.014567,"winner":"REPUBLICAN","color":"#ef3b2c"},"15":{"district":"15","dem_votes":12722,"rep_votes":27341,"other_votes":3758,"total_votes":43821,"dem_candidate":"Hillary Clinton and Tim Kaine","rep_candidate":"Donald J. Trump and Michael R. Pence","margin":14619,"margin_pct":33.360717,"winner":"REPUBLICAN","color":"#a50f15"},"16":{"district":"16","dem_votes":13290,"rep_votes":26017,"other_votes":3364,"total_votes":42671,"dem_candidate":"Hillary Clinton and Tim Kaine","rep_candidate":"Donald J. Trump and Michael R. Pence","margin":12727,"margin_pct":29.825877,"winner":"REPUBLICAN","color":"#cb181d"},"17":{"district":"17","dem_votes":11856,"rep_votes":29334,"other_votes":3853,"total_votes":45043,"dem_candidate":"Hillary Clinton and Tim Kaine","rep_candidate":"Donald J. Trump and Michael R. Pence","margin":17478,"margin_pct":38.802922,"winner":"REPUBLICAN","color":"#a50f15"},"18":{"district":"18","dem_votes":19136,"rep_votes":18437,"other_votes":4404,"total_votes":41977,"dem_candidate":"Hillary Clinton and Tim Kaine","rep_candidate":"Donald J. Trump and Michael R. Pence","margin":-699,"margin_pct":-1.665198,"winner":"DEMOCRAT","color":"#c6dbef"},"19":{"district":"19","dem_votes":13758,"rep_votes":24313,"other_votes":3625,"total_votes":41696,"dem_candidate":"Hillary Clinton and Tim Kaine","rep_candidate":"Donald J. Trump and Michael R. Pence","margin":10555,"margin_pct":25.314179,"winner":"REPUBLICAN","color":"#cb181d"},"20":{"district":"20","dem_votes":15459,"rep_votes":24658,"other_votes":3875,"total_votes":43992,"dem_candidate":"Hillary Clinton and Tim Kaine","rep_candidate":"Donald J. Trump and Michael R. Pence","margin":9199,"margin_pct":20.91062,"winner":"REPUBLICAN","color":"#cb181d"},"21":{"district":"21","dem_votes":11607,"rep_votes":25732,"other_votes":2945,"total_votes":40284,"dem_candidate":"Hillary Clinton and Tim Kaine","rep_candidate":"Donald J. Trump and Michael R. Pence","margin":14125,"margin_pct":35.063549,"winner":"REPUBLICAN","color":"#a50f15"},"22":{"district":"22","dem_votes":13367,"rep_votes":27617,"other_votes":3523,"total_votes":44507,"dem_candidate":"Hillary Clinton and Tim Kaine","rep_candidate":"Donald J. Trump and Michael R. Pence","margin":14250,"margin_pct":32.017435,"winner":"REPUBLICAN","color":"#a50f15"},"23":{"district":"23","dem_votes":15774,"rep_votes":22681,"other_votes":3315,"total_votes":41770,"dem_candidate":"Hillary Clinton and Tim Kaine","rep_candidate":"Donald J. Trump and Michael R. Pence","margin":6907,"margin_pct":16.535791,"winner":"REPUBLICAN","color":"#ef3b2c"},"24":{"district":"24","dem_votes":16558,"rep_votes":21409,"other_votes":4060,"total_votes":42027,"dem_candidate":"Hillary Clinton and Tim Kaine","rep_candidate":"Donald J. Trump and Michael R. Pence","margin":4851,"margin_pct":11.54258,"winner":"REPUBLICAN","color":"#ef3b2c"},"25":{"district":"25","dem_votes":20375,"rep_votes":16165,"other_votes":4416,"total_votes":40956,"dem_candidate":"Hillary Clinton and Tim Kaine","rep_candidate":"Donald J. Trump and Michael R. Pence","margin":-4210,"margin_pct":-10.279324,"winner":"DEMOCRAT","color":"#6baed6"},"26":{"district":"26","dem_votes":19218,"rep_votes":23868,"other_votes":4310,"total_votes":47396,"dem_candidate":"Hillary Clinton and Tim Kaine","rep_candidate":"Donald J. Trump and Michael R. Pence","margin":4650,"margin_pct":9.810955,"winner":"REPUBLICAN","color":"#fb6a4a"},"27":{"district":"27","dem_votes":11060,"rep_votes":29078,"other_votes":3478,"total_votes":43616,"dem_candidate":"Hillary Clinton and Tim Kaine","rep_candidate":"Donald J. Trump and Michael R. Pence","margin":18018,"margin_pct":41.310528,"winner":"REPUBLICAN","color":"#67000d"},"28":{"district":"28","dem_votes":12807,"rep_votes":26802,"other_votes":3561,"total_votes":43170,"dem_candidate":"Hillary Clinton and Tim Kaine","rep_candidate":"Donald J. Trump and Michael R. Pence","margin":13995,"margin_pct":32.418346,"winner":"REPUBLICAN","color":"#a50f15"},"29":{"district":"29","dem_votes":14848,"rep_votes":31403,"other_votes":4347,"total_votes":50598,"dem_candidate":"Hillary Clinton and Tim Kaine","rep_candidate":"Donald J. Trump and Michael R. Pence","margin":16555,"margin_pct":32.718685,"winner":"REPUBLICAN","color":"#a50f15"},"30":{"district":"30","dem_votes":10743,"rep_votes":22208,"other_votes":3052,"total_votes":36003,"dem_candidate":"Hillary Clinton and Tim Kaine","rep_candidate":"Donald J. Trump and Michael R. Pence","margin":11465,"margin_pct":31.844569,"winner":"REPUBLICAN","color":"#a50f15"},"31":{"district":"31","dem_votes":14093,"rep_votes":26883,"other_votes":3816,"total_votes":44792,"dem_candidate":"Hillary Clinton and Tim Kaine","rep_candidate":"Donald J. Trump and Michael R. Pence","margin":12790,"margin_pct":28.554206,"winner":"REPUBLICAN","color":"#cb181d"},"32":{"district":"32","dem_votes":17939,"rep_votes":22028,"other_votes":3925,"total_votes":43892,"dem_candidate":"Hillary Clinton and Tim Kaine","rep_candidate":"Donald J. Trump and Michael R. Pence","margin":4089,"margin_pct":9.316048,"winner":"REPUBLICAN","color":"#fb6a4a"},"33":{"district":"33","dem_votes":22433,"rep_votes":24935,"other_votes":4636,"total_votes":52004,"dem_candidate":"Hillary Clinton and Tim Kaine","rep_candidate":"Donald J. Trump and Michael R. Pence","margin":2502,"margin_pct":4.811168,"winner":"REPUBLICAN","color":"#fcae91"},"34":{"district":"34","dem_votes":22548,"rep_votes":19831,"other_votes":3959,"total_votes":46338,"dem_candidate":"Hillary Clinton and Tim Kaine","rep_candidate":"Donald J. Trump and Michael R. Pence","margin":-2717,"margin_pct":-5.863438,"winner":"DEMOCRAT","color":"#9ecae1"},"35":{"district":"35","dem_votes":18427,"rep_votes":21082,"other_votes":4235,"total_votes":43744,"dem_candidate":"Hillary Clinton and Tim Kaine","rep_candidate":"Donald J. Trump and Michael R. Pence","margin":2655,"margin_pct":6.069404,"winner":"REPUBLICAN","color":"#fb6a4a"},"36":{"district":"36","dem_votes":35421,"rep_votes":25417,"other_votes":6060,"total_votes":66898,"dem_candidate":"Hillary Clinton and Tim Kaine","rep_candidate":"Donald J. Trump and Michael R. Pence","margin":-10004,"margin_pct":-14.954109,"winner":"DEMOCRAT","color":"#6baed6"},"37":{"district":"37","dem_votes":24043,"rep_votes":24547,"other_votes":4805,"total_votes":53395,"dem_candidate":"Hillary Clinton and Tim Kaine","rep_candidate":"Donald J. Trump and Michael R. Pence","margin":504,"margin_pct":0.943909,"winner":"REPUBLICAN","color":"#fee8c8"},"38":{"district":"38","dem_votes":23455,"rep_votes":9942,"other_votes":2762,"total_votes":36159,"dem_candidate":"Hillary Clinton and Tim Kaine","rep_candidate":"Donald J. Trump and Michael R. Pence","margin":-13513,"margin_pct":-37.371056,"winner":"DEMOCRAT","color":"#08519c"},"39":{"district":"39","dem_votes":23378,"rep_votes":12608,"other_votes":3842,"total_votes":39828,"dem_candidate":"Hillary Clinton and Tim Kaine","rep_candidate":"Donald J. Trump and Michael R. Pence","margin":-10770,"margin_pct":-27.041277,"winner":"DEMOCRAT","color":"#3182bd"},"40":{"district":"40","dem_votes":43453,"rep_votes":21077,"other_votes":6853,"total_votes":71383,"dem_candidate":"Hillary Clinton and Tim Kaine","rep_candidate":"Donald J. Trump and Michael R. Pence","margin":-22376,"margin_pct":-31.346399,"winner":"DEMOCRAT","color":"#08519c"},"41":{"district":"41","dem_votes":20906,"rep_votes":22188,"other_votes":4299,"total_votes":47393,"dem_candidate":"Hillary Clinton and Tim Kaine","rep_candidate":"Donald J. Trump and Michael R. Pence","margin":1282,"margin_pct":2.705041,"winner":"REPUBLICAN","color":"#fcae91"},"42":{"district":"42","dem_votes":26017,"rep_votes":18006,"other_votes":4320,"total_votes":48343,"dem_candidate":"Hillary Clinton and Tim Kaine","rep_candidate":"Donald J. Trump and Michael R. Pence","margin":-8011,"margin_pct":-16.571169,"winner":"DEMOCRAT","color":"#6baed6"},"43":{"district":"43","dem_votes":24901,"rep_votes":12112,"other_votes":3800,"total_votes":40813,"dem_candidate":"Hillary Clinton and Tim Kaine","rep_candidate":"Donald J. Trump and Michael R. Pence","margin":-12789,"margin_pct":-31.335604,"winner":"DEMOCRAT","color":"#08519c"},"44":{"district":"44","dem_votes":29828,"rep_votes":16305,"other_votes":4410,"total_votes":50543,"dem_candidate":"Hillary Clinton and Tim Kaine","rep_candidate":"Donald J. Trump and Michael R. Pence","margin":-13523,"margin_pct":-26.755436,"winner":"DEMOCRAT","color":"#3182bd"},"45":{"district":"45","dem_votes":28571,"rep_votes":22555,"other_votes":4969,"total_votes":56095,"dem_candidate":"Hillary Clinton and Tim Kaine","rep_candidate":"Donald J. Trump and Michael R. Pence","margin":-6016,"margin_pct":-10.724664,"winner":"DEMOCRAT","color":"#6baed6"},"46":{"district":"46","dem_votes":12647,"rep_votes":5553,"other_votes":1833,"total_votes":20033,"dem_candidate":"Hillary Clinton and Tim Kaine","rep_candidate":"Donald J. Trump and Michael R. Pence","margin":-7094,"margin_pct":-35.411571,"winner":"DEMOCRAT","color":"#08519c"},"47":{"district":"47","dem_votes":23401,"rep_votes":17139,"other_votes":3792,"total_votes":44332,"dem_candidate":"Hillary Clinton and Tim Kaine","rep_candidate":"Donald J. Trump and Michael R. Pence","margin":-6262,"margin_pct":-14.125237,"winner":"DEMOCRAT","color":"#6baed6"},"48":{"district":"48","dem_votes":18338,"rep_votes":22073,"other_votes":4227,"total_votes":44638,"dem_candidate":"Hillary Clinton and Tim Kaine","rep_candidate":"Donald J. Trump and Michael R. Pence","margin":3735,"margin_pct":8.36731,"winner":"REPUBLICAN","color":"#fb6a4a"},"49":{"district":"49","dem_votes":28919,"rep_votes":19260,"other_votes":4665,"total_votes":52844,"dem_candidate":"Hillary Clinton and Tim Kaine","rep_candidate":"Donald J. Trump and Michael R. Pence","margin":-9659,"margin_pct":-18.278329,"winner":"DEMOCRAT","color":"#6baed6"},"50":{"district":"50","dem_votes":31424,"rep_votes":17914,"other_votes":4598,"total_votes":53936,"dem_candidate":"Hillary Clinton and Tim Kaine","rep_candidate":"Donald J. Trump and Michael R. Pence","margin":-13510,"margin_pct":-25.048205,"winner":"DEMOCRAT","color":"#3182bd"},"51":{"district":"51","dem_votes":30145,"rep_votes":14361,"other_votes":4362,"total_votes":48868,"dem_candidate":"Hillary Clinton and Tim Kaine","rep_candidate":"Donald J. Trump and Michael R. Pence","margin":-15784,"margin_pct":-32.299255,"winner":"DEMOCRAT","color":"#08519c"},"52":{"district":"52","dem_votes":27212,"rep_votes":18833,"other_votes":4910,"total_votes":50955,"dem_candidate":"Hillary Clinton and Tim Kaine","rep_candidate":"Donald J. Trump and Michael R. Pence","margin":-8379,"margin_pct":-16.443921,"winner":"DEMOCRAT","color":"#6baed6"},"53":{"district":"53","dem_votes":7073,"rep_votes":5810,"other_votes":1379,"total_votes":14262,"dem_candidate":"Hillary Clinton and Tim Kaine","rep_candidate":"Donald J. Trump and Michael R. Pence","margin":-1263,"margin_pct":-8.8557,"winner":"DEMOCRAT","color":"#9ecae1"},"54":{"district":"54","dem_votes":16082,"rep_votes":21468,"other_votes":3758,"total_votes":41308,"dem_candidate":"Hillary Clinton and Tim Kaine","rep_candidate":"Donald J. Trump and Michael R. Pence","margin":5386,"margin_pct":13.038637,"winner":"REPUBLICAN","color":"#ef3b2c"},"55":{"district":"55","dem_votes":22957,"rep_votes":19410,"other_votes":4247,"total_votes":46614,"dem_candidate":"Hillary Clinton and Tim Kaine","rep_candidate":"Donald J. Trump and Michael R. Pence","margin":-3547,"margin_pct":-7.609302,"winner":"DEMOCRAT","color":"#9ecae1"},"56":{"district":"56","dem_votes":25119,"rep_votes":20741,"other_votes":4656,"total_votes":50516,"dem_candidate":"Hillary Clinton and Tim Kaine","rep_candidate":"Donald J. Trump and Michael R. Pence","margin":-4378,"margin_pct":-8.666561,"winner":"DEMOCRAT","color":"#9ecae1"},"57":{"district":"57","dem_votes":19821,"rep_votes":26085,"other_votes":4303,"total_votes":50209,"dem_candidate":"Hillary Clinton and Tim Kaine","rep_candidate":"Donald J. Trump and Michael R. Pence","margin":6264,"margin_pct":12.475851,"winner":"REPUBLICAN","color":"#ef3b2c"},"58":{"district":"58","dem_votes":23033,"rep_votes":25193,"other_votes":4449,"total_votes":52675,"dem_candidate":"Hillary Clinton and Tim Kaine","rep_candidate":"Donald J. Trump and Michael R. Pence","margin":2160,"margin_pct":4.100617,"winner":"REPUBLICAN","color":"#fcae91"},"59":{"district":"59","dem_votes":29573,"rep_votes":5095,"other_votes":3065,"total_votes":37733,"dem_candidate":"Hillary Clinton and Tim Kaine","rep_candidate":"Donald J. Trump and Michael R. Pence","margin":-24478,"margin_pct":-64.871598,"winner":"DEMOCRAT","color":"#08306b"},"60":{"district":"60","dem_votes":32583,"rep_votes":6324,"other_votes":4270,"total_votes":43177,"dem_candidate":"Hillary Clinton and Tim Kaine","rep_candidate":"Donald J. Trump and Michael R. Pence","margin":-26259,"margin_pct":-60.817102,"winner":"DEMOCRAT","color":"#08306b"},"61":{"district":"61","dem_votes":37481,"rep_votes":6170,"other_votes":3717,"total_votes":47368,"dem_candidate":"Hillary Clinton and Tim Kaine","rep_candidate":"Donald J. Trump and Michael R. Pence","margin":-31311,"margin_pct":-66.101588,"winner":"DEMOCRAT","color":"#08306b"},"62":{"district":"62","dem_votes":33091,"rep_votes":3297,"other_votes":3458,"total_votes":39846,"dem_candidate":"Hillary Clinton and Tim Kaine","rep_candidate":"Donald J. Trump and Michael R. Pence","margin":-29794,"margin_pct":-74.772876,"winner":"DEMOCRAT","color":"#08306b"},"63":{"district":"63","dem_votes":44502,"rep_votes":7299,"other_votes":4442,"total_votes":56243,"dem_candidate":"Hillary Clinton and Tim Kaine","rep_candidate":"Donald J. Trump and Michael R. Pence","margin":-37203,"margin_pct":-66.146898,"winner":"DEMOCRAT","color":"#08306b"},"64":{"district":"64","dem_votes":17585,"rep_votes":4417,"other_votes":2053,"total_votes":24055,"dem_candidate":"Hillary Clinton and Tim Kaine","rep_candidate":"Donald J. Trump and Michael R. Pence","margin":-13168,"margin_pct":-54.741218,"winner":"DEMOCRAT","color":"#08306b"},"65":{"district":"65","dem_votes":18547,"rep_votes":4991,"other_votes":2211,"total_votes":25749,"dem_candidate":"Hillary Clinton and Tim Kaine","rep_candidate":"Donald J. Trump and Michael R. Pence","margin":-13556,"margin_pct":-52.646705,"winner":"DEMOCRAT","color":"#08306b"},"66":{"district":"66","dem_votes":24229,"rep_votes":6543,"other_votes":2917,"total_votes":33689,"dem_candidate":"Hillary Clinton and Tim Kaine","rep_candidate":"Donald J. Trump and Michael R. Pence","margin":-17686,"margin_pct":-52.497848,"winner":"DEMOCRAT","color":"#08306b"},"67":{"district":"67","dem_votes":13801,"rep_votes":3466,"other_votes":1611,"total_votes":18878,"dem_candidate":"Hillary Clinton and Tim Kaine","rep_candidate":"Donald J. Trump and Michael R. Pence","margin":-10335,"margin_pct":-54.746265,"winner":"DEMOCRAT","color":"#08306b"}}},"meta":{"source_file":"20161108__mn__general__precinct.csv","crosswalk_file":"precinct_to_2022_state_senate.csv","generated_at_utc":"2026-03-22T20:06:41Z","total_input_votes":2944813,"crosswalk_matched_votes":2494724,"fallback_matched_votes":0,"county_fallback_votes":450089,"unmatched_votes":0,"match_coverage_pct":100.0,"crosswalk_match_pct":84.7159}}