{"contest_type":"president","year":2000,"state":"MN","rows":[{"county":"Aitkin","dem_votes":3830,"rep_votes":3755,"other_votes":433,"total_votes":8018,"dem_candidate":"Al Gore","rep_candidate":"George W. Bush","margin":-75,"margin_pct":-0.935395,"winner":"DEMOCRAT","color":"#e1f5fe"},{"county":"Anoka","dem_votes":68008,"rep_votes":69256,"other_votes":7052,"total_votes":144316,"dem_candidate":"Al Gore","rep_candidate":"George W. Bush","margin":1248,"margin_pct":0.864769,"winner":"REPUBLICAN","color":"#fee8c8"},{"county":"Becker","dem_votes":5253,"rep_votes":8152,"other_votes":635,"total_votes":14040,"dem_candidate":"Al Gore","rep_candidate":"George W. Bush","margin":2899,"margin_pct":20.648148,"winner":"REPUBLICAN","color":"#cb181d"},{"county":"Beltrami","dem_votes":7301,"rep_votes":8346,"other_votes":1328,"total_votes":16975,"dem_candidate":"Al Gore","rep_candidate":"George W. Bush","margin":1045,"margin_pct":6.156112,"winner":"REPUBLICAN","color":"#fb6a4a"},{"county":"Benton","dem_votes":6009,"rep_votes":7663,"other_votes":914,"total_votes":14586,"dem_candidate":"Al Gore","rep_candidate":"George W. Bush","margin":1654,"margin_pct":11.339641,"winner":"REPUBLICAN","color":"#ef3b2c"},{"county":"Big Stone","dem_votes":1430,"rep_votes":1370,"other_votes":116,"total_votes":2916,"dem_candidate":"Al Gore","rep_candidate":"George W. Bush","margin":-60,"margin_pct":-2.057613,"winner":"DEMOCRAT","color":"#c6dbef"},{"county":"Blue Earth","dem_votes":12329,"rep_votes":12942,"other_votes":1847,"total_votes":27118,"dem_candidate":"Al Gore","rep_candidate":"George W. Bush","margin":613,"margin_pct":2.260491,"winner":"REPUBLICAN","color":"#fcae91"},{"county":"Brown","dem_votes":4650,"rep_votes":7370,"other_votes":587,"total_votes":12607,"dem_candidate":"Al Gore","rep_candidate":"George W. Bush","margin":2720,"margin_pct":21.575315,"winner":"REPUBLICAN","color":"#cb181d"},{"county":"Carlton","dem_votes":8620,"rep_votes":5578,"other_votes":674,"total_votes":14872,"dem_candidate":"Al Gore","rep_candidate":"George W. Bush","margin":-3042,"margin_pct":-20.454545,"winner":"DEMOCRAT","color":"#3182bd"},{"county":"Carver","dem_votes":12462,"rep_votes":20790,"other_votes":1495,"total_votes":34747,"dem_candidate":"Al Gore","rep_candidate":"George W. Bush","margin":8328,"margin_pct":23.967537,"winner":"REPUBLICAN","color":"#cb181d"},{"county":"Cass","dem_votes":5534,"rep_votes":7134,"other_votes":697,"total_votes":13365,"dem_candidate":"Al Gore","rep_candidate":"George W. Bush","margin":1600,"margin_pct":11.971568,"winner":"REPUBLICAN","color":"#ef3b2c"},{"county":"Chippewa","dem_votes":2952,"rep_votes":2977,"other_votes":290,"total_votes":6219,"dem_candidate":"Al Gore","rep_candidate":"George W. Bush","margin":25,"margin_pct":0.401994,"winner":"REPUBLICAN","color":"#f7f7f7"},{"county":"Chisago","dem_votes":9593,"rep_votes":10937,"other_votes":1178,"total_votes":21708,"dem_candidate":"Al Gore","rep_candidate":"George W. Bush","margin":1344,"margin_pct":6.191266,"winner":"REPUBLICAN","color":"#fb6a4a"},{"county":"Clay","dem_votes":10128,"rep_votes":11712,"other_votes":1043,"total_votes":22883,"dem_candidate":"Al Gore","rep_candidate":"George W. Bush","margin":1584,"margin_pct":6.922169,"winner":"REPUBLICAN","color":"#fb6a4a"},{"county":"Clearwater","dem_votes":1466,"rep_votes":2137,"other_votes":143,"total_votes":3746,"dem_candidate":"Al Gore","rep_candidate":"George W. Bush","margin":671,"margin_pct":17.91244,"winner":"REPUBLICAN","color":"#ef3b2c"},{"county":"Cook","dem_votes":1171,"rep_votes":1295,"other_votes":303,"total_votes":2769,"dem_candidate":"Al Gore","rep_candidate":"George W. Bush","margin":124,"margin_pct":4.478151,"winner":"REPUBLICAN","color":"#fcae91"},{"county":"Cottonwood","dem_votes":2503,"rep_votes":3369,"other_votes":219,"total_votes":6091,"dem_candidate":"Al Gore","rep_candidate":"George W. Bush","margin":866,"margin_pct":14.217698,"winner":"REPUBLICAN","color":"#ef3b2c"},{"county":"Crow Wing","dem_votes":11255,"rep_votes":15035,"other_votes":1384,"total_votes":27674,"dem_candidate":"Al Gore","rep_candidate":"George W. Bush","margin":3780,"margin_pct":13.65903,"winner":"REPUBLICAN","color":"#ef3b2c"},{"county":"Dakota","dem_votes":85446,"rep_votes":87250,"other_votes":8318,"total_votes":181014,"dem_candidate":"Al Gore","rep_candidate":"George W. Bush","margin":1804,"margin_pct":0.996608,"winner":"REPUBLICAN","color":"#fee8c8"},{"county":"Dodge","dem_votes":3370,"rep_votes":4213,"other_votes":354,"total_votes":7937,"dem_candidate":"Al Gore","rep_candidate":"George W. Bush","margin":843,"margin_pct":10.621141,"winner":"REPUBLICAN","color":"#ef3b2c"},{"county":"Douglas","dem_votes":6352,"rep_votes":9811,"other_votes":788,"total_votes":16951,"dem_candidate":"Al Gore","rep_candidate":"George W. Bush","margin":3459,"margin_pct":20.405876,"winner":"REPUBLICAN","color":"#cb181d"},{"county":"Faribault","dem_votes":3624,"rep_votes":4336,"other_votes":326,"total_votes":8286,"dem_candidate":"Al Gore","rep_candidate":"George W. Bush","margin":712,"margin_pct":8.592807,"winner":"REPUBLICAN","color":"#fb6a4a"},{"county":"Fillmore","dem_votes":5020,"rep_votes":4646,"other_votes":451,"total_votes":10117,"dem_candidate":"Al Gore","rep_candidate":"George W. Bush","margin":-374,"margin_pct":-3.696748,"winner":"DEMOCRAT","color":"#c6dbef"},{"county":"Freeborn","dem_votes":8514,"rep_votes":6843,"other_votes":608,"total_votes":15965,"dem_candidate":"Al Gore","rep_candidate":"George W. Bush","margin":-1671,"margin_pct":-10.466646,"winner":"DEMOCRAT","color":"#6baed6"},{"county":"Goodhue","dem_votes":9981,"rep_votes":10852,"other_votes":1147,"total_votes":21980,"dem_candidate":"Al Gore","rep_candidate":"George W. Bush","margin":871,"margin_pct":3.962693,"winner":"REPUBLICAN","color":"#fcae91"},{"county":"Grant","dem_votes":1507,"rep_votes":1804,"other_votes":225,"total_votes":3536,"dem_candidate":"Al Gore","rep_candidate":"George W. Bush","margin":297,"margin_pct":8.399321,"winner":"REPUBLICAN","color":"#fb6a4a"},{"county":"Hennepin","dem_votes":307599,"rep_votes":225657,"other_votes":37607,"total_votes":570863,"dem_candidate":"Al Gore","rep_candidate":"George W. Bush","margin":-81942,"margin_pct":-14.354057,"winner":"DEMOCRAT","color":"#6baed6"},{"county":"Houston","dem_votes":4502,"rep_votes":5077,"other_votes":458,"total_votes":10037,"dem_candidate":"Al Gore","rep_candidate":"George W. Bush","margin":575,"margin_pct":5.728803,"winner":"REPUBLICAN","color":"#fb6a4a"},{"county":"Hubbard","dem_votes":3632,"rep_votes":5307,"other_votes":521,"total_votes":9460,"dem_candidate":"Al Gore","rep_candidate":"George W. Bush","margin":1675,"margin_pct":17.706131,"winner":"REPUBLICAN","color":"#ef3b2c"},{"county":"Isanti","dem_votes":6247,"rep_votes":7668,"other_votes":810,"total_votes":14725,"dem_candidate":"Al Gore","rep_candidate":"George W. Bush","margin":1421,"margin_pct":9.650255,"winner":"REPUBLICAN","color":"#fb6a4a"},{"county":"Itasca","dem_votes":10583,"rep_votes":9545,"other_votes":1223,"total_votes":21351,"dem_candidate":"Al Gore","rep_candidate":"George W. Bush","margin":-1038,"margin_pct":-4.861599,"winner":"DEMOCRAT","color":"#c6dbef"},{"county":"Jackson","dem_votes":2364,"rep_votes":2773,"other_votes":210,"total_votes":5347,"dem_candidate":"Al Gore","rep_candidate":"George W. Bush","margin":409,"margin_pct":7.649149,"winner":"REPUBLICAN","color":"#fb6a4a"},{"county":"Kanabec","dem_votes":2831,"rep_votes":3480,"other_votes":372,"total_votes":6683,"dem_candidate":"Al Gore","rep_candidate":"George W. Bush","margin":649,"margin_pct":9.711208,"winner":"REPUBLICAN","color":"#fb6a4a"},{"county":"Kandiyohi","dem_votes":8220,"rep_votes":10026,"other_votes":777,"total_votes":19023,"dem_candidate":"Al Gore","rep_candidate":"George W. Bush","margin":1806,"margin_pct":9.493771,"winner":"REPUBLICAN","color":"#fb6a4a"},{"county":"Kittson","dem_votes":1107,"rep_votes":1353,"other_votes":77,"total_votes":2537,"dem_candidate":"Al Gore","rep_candidate":"George W. Bush","margin":246,"margin_pct":9.696492,"winner":"REPUBLICAN","color":"#fb6a4a"},{"county":"Koochiching","dem_votes":2903,"rep_votes":3523,"other_votes":335,"total_votes":6761,"dem_candidate":"Al Gore","rep_candidate":"George W. Bush","margin":620,"margin_pct":9.170241,"winner":"REPUBLICAN","color":"#fb6a4a"},{"county":"Lac qui Parle","dem_votes":2244,"rep_votes":1941,"other_votes":171,"total_votes":4356,"dem_candidate":"Al Gore","rep_candidate":"George W. Bush","margin":-303,"margin_pct":-6.955923,"winner":"DEMOCRAT","color":"#9ecae1"},{"county":"Lake","dem_votes":3579,"rep_votes":2465,"other_votes":450,"total_votes":6494,"dem_candidate":"Al Gore","rep_candidate":"George W. Bush","margin":-1114,"margin_pct":-17.154296,"winner":"DEMOCRAT","color":"#6baed6"},{"county":"Lake of the Woods","dem_votes":848,"rep_votes":1216,"other_votes":83,"total_votes":2147,"dem_candidate":"Al Gore","rep_candidate":"George W. Bush","margin":368,"margin_pct":17.140196,"winner":"REPUBLICAN","color":"#ef3b2c"},{"county":"Le Sueur","dem_votes":5361,"rep_votes":6138,"other_votes":633,"total_votes":12132,"dem_candidate":"Al Gore","rep_candidate":"George W. Bush","margin":777,"margin_pct":6.40455,"winner":"REPUBLICAN","color":"#fb6a4a"},{"county":"Lincoln","dem_votes":1590,"rep_votes":1513,"other_votes":113,"total_votes":3216,"dem_candidate":"Al Gore","rep_candidate":"George W. Bush","margin":-77,"margin_pct":-2.394279,"winner":"DEMOCRAT","color":"#c6dbef"},{"county":"Lyon","dem_votes":4737,"rep_votes":6087,"other_votes":487,"total_votes":11311,"dem_candidate":"Al Gore","rep_candidate":"George W. Bush","margin":1350,"margin_pct":11.935284,"winner":"REPUBLICAN","color":"#ef3b2c"},{"county":"Mahnomen","dem_votes":921,"rep_votes":1122,"other_votes":106,"total_votes":2149,"dem_candidate":"Al Gore","rep_candidate":"George W. Bush","margin":201,"margin_pct":9.353188,"winner":"REPUBLICAN","color":"#fb6a4a"},{"county":"Marshall","dem_votes":1910,"rep_votes":2912,"other_votes":169,"total_votes":4991,"dem_candidate":"Al Gore","rep_candidate":"George W. Bush","margin":1002,"margin_pct":20.076137,"winner":"REPUBLICAN","color":"#cb181d"},{"county":"Martin","dem_votes":4166,"rep_votes":5686,"other_votes":398,"total_votes":10250,"dem_candidate":"Al Gore","rep_candidate":"George W. Bush","margin":1520,"margin_pct":14.829268,"winner":"REPUBLICAN","color":"#ef3b2c"},{"county":"McLeod","dem_votes":5609,"rep_votes":8782,"other_votes":734,"total_votes":15125,"dem_candidate":"Al Gore","rep_candidate":"George W. Bush","margin":3173,"margin_pct":20.978512,"winner":"REPUBLICAN","color":"#cb181d"},{"county":"Meeker","dem_votes":2771,"rep_votes":2808,"other_votes":278,"total_votes":5857,"dem_candidate":"Al Gore","rep_candidate":"George W. Bush","margin":37,"margin_pct":0.631723,"winner":"REPUBLICAN","color":"#fee8c8"},{"county":"Mille Lacs","dem_votes":4402,"rep_votes":5520,"other_votes":534,"total_votes":10456,"dem_candidate":"Al Gore","rep_candidate":"George W. Bush","margin":1118,"margin_pct":10.692425,"winner":"REPUBLICAN","color":"#ef3b2c"},{"county":"Morrison","dem_votes":4376,"rep_votes":5223,"other_votes":477,"total_votes":10076,"dem_candidate":"Al Gore","rep_candidate":"George W. Bush","margin":847,"margin_pct":8.406114,"winner":"REPUBLICAN","color":"#fb6a4a"},{"county":"Mower","dem_votes":5274,"rep_votes":8197,"other_votes":676,"total_votes":14147,"dem_candidate":"Al Gore","rep_candidate":"George W. Bush","margin":2923,"margin_pct":20.661624,"winner":"REPUBLICAN","color":"#cb181d"},{"county":"Murray","dem_votes":10693,"rep_votes":6873,"other_votes":722,"total_votes":18288,"dem_candidate":"Al Gore","rep_candidate":"George W. Bush","margin":-3820,"margin_pct":-20.888014,"winner":"DEMOCRAT","color":"#3182bd"},{"county":"Nicollet","dem_votes":2093,"rep_votes":2407,"other_votes":161,"total_votes":4661,"dem_candidate":"Al Gore","rep_candidate":"George W. Bush","margin":314,"margin_pct":6.736752,"winner":"REPUBLICAN","color":"#fb6a4a"},{"county":"Nobles","dem_votes":7041,"rep_votes":7221,"other_votes":877,"total_votes":15139,"dem_candidate":"Al Gore","rep_candidate":"George W. Bush","margin":180,"margin_pct":1.188982,"winner":"REPUBLICAN","color":"#fcae91"},{"county":"Norman","dem_votes":3760,"rep_votes":4766,"other_votes":259,"total_votes":8785,"dem_candidate":"Al Gore","rep_candidate":"George W. Bush","margin":1006,"margin_pct":11.451338,"winner":"REPUBLICAN","color":"#ef3b2c"},{"county":"Olmsted","dem_votes":1575,"rep_votes":1808,"other_votes":134,"total_votes":3517,"dem_candidate":"Al Gore","rep_candidate":"George W. Bush","margin":233,"margin_pct":6.624964,"winner":"REPUBLICAN","color":"#fb6a4a"},{"county":"Otter Tail","dem_votes":25822,"rep_votes":30641,"other_votes":2449,"total_votes":58912,"dem_candidate":"Al Gore","rep_candidate":"George W. Bush","margin":4819,"margin_pct":8.179997,"winner":"REPUBLICAN","color":"#fb6a4a"},{"county":"Pennington","dem_votes":9844,"rep_votes":16963,"other_votes":1190,"total_votes":27997,"dem_candidate":"Al Gore","rep_candidate":"George W. Bush","margin":7119,"margin_pct":25.427724,"winner":"REPUBLICAN","color":"#cb181d"},{"county":"Pine","dem_votes":2458,"rep_votes":3380,"other_votes":276,"total_votes":6114,"dem_candidate":"Al Gore","rep_candidate":"George W. Bush","margin":922,"margin_pct":15.080144,"winner":"REPUBLICAN","color":"#ef3b2c"},{"county":"Pipestone","dem_votes":6148,"rep_votes":5854,"other_votes":778,"total_votes":12780,"dem_candidate":"Al Gore","rep_candidate":"George W. Bush","margin":-294,"margin_pct":-2.300469,"winner":"DEMOCRAT","color":"#c6dbef"},{"county":"Polk","dem_votes":1970,"rep_votes":2693,"other_votes":151,"total_votes":4814,"dem_candidate":"Al Gore","rep_candidate":"George W. Bush","margin":723,"margin_pct":15.018695,"winner":"REPUBLICAN","color":"#ef3b2c"},{"county":"Pope","dem_votes":5764,"rep_votes":7609,"other_votes":403,"total_votes":13776,"dem_candidate":"Al Gore","rep_candidate":"George W. Bush","margin":1845,"margin_pct":13.392857,"winner":"REPUBLICAN","color":"#ef3b2c"},{"county":"Ramsey","dem_votes":138470,"rep_votes":87669,"other_votes":16299,"total_votes":242438,"dem_candidate":"Al Gore","rep_candidate":"George W. Bush","margin":-50801,"margin_pct":-20.954223,"winner":"DEMOCRAT","color":"#3182bd"},{"county":"Red Lake","dem_votes":830,"rep_votes":1090,"other_votes":70,"total_votes":1990,"dem_candidate":"Al Gore","rep_candidate":"George W. Bush","margin":260,"margin_pct":13.065327,"winner":"REPUBLICAN","color":"#ef3b2c"},{"county":"Redwood","dem_votes":2681,"rep_votes":4589,"other_votes":332,"total_votes":7602,"dem_candidate":"Al Gore","rep_candidate":"George W. Bush","margin":1908,"margin_pct":25.098658,"winner":"REPUBLICAN","color":"#cb181d"},{"county":"Renville","dem_votes":3533,"rep_votes":4036,"other_votes":366,"total_votes":7935,"dem_candidate":"Al Gore","rep_candidate":"George W. Bush","margin":503,"margin_pct":6.339004,"winner":"REPUBLICAN","color":"#fb6a4a"},{"county":"Rice","dem_votes":13140,"rep_votes":10876,"other_votes":1721,"total_votes":25737,"dem_candidate":"Al Gore","rep_candidate":"George W. Bush","margin":-2264,"margin_pct":-8.796674,"winner":"DEMOCRAT","color":"#9ecae1"},{"county":"Rock","dem_votes":2081,"rep_votes":2772,"other_votes":123,"total_votes":4976,"dem_candidate":"Al Gore","rep_candidate":"George W. Bush","margin":691,"margin_pct":13.886656,"winner":"REPUBLICAN","color":"#ef3b2c"},{"county":"Roseau","dem_votes":2128,"rep_votes":4695,"other_votes":206,"total_votes":7029,"dem_candidate":"Al Gore","rep_candidate":"George W. Bush","margin":2567,"margin_pct":36.520131,"winner":"REPUBLICAN","color":"#a50f15"},{"county":"Scott","dem_votes":17503,"rep_votes":23954,"other_votes":1968,"total_votes":43425,"dem_candidate":"Al Gore","rep_candidate":"George W. Bush","margin":6451,"margin_pct":14.855498,"winner":"REPUBLICAN","color":"#ef3b2c"},{"county":"Sherburne","dem_votes":12109,"rep_votes":16813,"other_votes":1585,"total_votes":30507,"dem_candidate":"Al Gore","rep_candidate":"George W. Bush","margin":4704,"margin_pct":15.419412,"winner":"REPUBLICAN","color":"#ef3b2c"},{"county":"Sibley","dem_votes":2687,"rep_votes":4087,"other_votes":383,"total_votes":7157,"dem_candidate":"Al Gore","rep_candidate":"George W. Bush","margin":1400,"margin_pct":19.561269,"winner":"REPUBLICAN","color":"#ef3b2c"},{"county":"St. Louis","dem_votes":64237,"rep_votes":35420,"other_votes":6604,"total_votes":106261,"dem_candidate":"Al Gore","rep_candidate":"George W. Bush","margin":-28817,"margin_pct":-27.119075,"winner":"DEMOCRAT","color":"#3182bd"},{"county":"Stearns","dem_votes":24800,"rep_votes":32402,"other_votes":4017,"total_votes":61219,"dem_candidate":"Al Gore","rep_candidate":"George W. Bush","margin":7602,"margin_pct":12.417713,"winner":"REPUBLICAN","color":"#ef3b2c"},{"county":"Steele","dem_votes":6900,"rep_votes":8223,"other_votes":736,"total_votes":15859,"dem_candidate":"Al Gore","rep_candidate":"George W. Bush","margin":1323,"margin_pct":8.342266,"winner":"REPUBLICAN","color":"#fb6a4a"},{"county":"Stevens","dem_votes":2434,"rep_votes":2831,"other_votes":410,"total_votes":5675,"dem_candidate":"Al Gore","rep_candidate":"George W. Bush","margin":397,"margin_pct":6.995595,"winner":"REPUBLICAN","color":"#fb6a4a"},{"county":"Swift","dem_votes":2698,"rep_votes":2376,"other_votes":233,"total_votes":5307,"dem_candidate":"Al Gore","rep_candidate":"George W. Bush","margin":-322,"margin_pct":-6.067458,"winner":"DEMOCRAT","color":"#9ecae1"},{"county":"Todd","dem_votes":4132,"rep_votes":6031,"other_votes":516,"total_votes":10679,"dem_candidate":"Al Gore","rep_candidate":"George W. Bush","margin":1899,"margin_pct":17.782564,"winner":"REPUBLICAN","color":"#ef3b2c"},{"county":"Traverse","dem_votes":884,"rep_votes":1074,"other_votes":89,"total_votes":2047,"dem_candidate":"Al Gore","rep_candidate":"George W. Bush","margin":190,"margin_pct":9.281876,"winner":"REPUBLICAN","color":"#fb6a4a"},{"county":"Wabasha","dem_votes":4522,"rep_votes":5245,"other_votes":606,"total_votes":10373,"dem_candidate":"Al Gore","rep_candidate":"George W. Bush","margin":723,"margin_pct":6.970018,"winner":"REPUBLICAN","color":"#fb6a4a"},{"county":"Wadena","dem_votes":2251,"rep_votes":3733,"other_votes":268,"total_votes":6252,"dem_candidate":"Al Gore","rep_candidate":"George W. Bush","margin":1482,"margin_pct":23.704415,"winner":"REPUBLICAN","color":"#cb181d"},{"county":"Waseca","dem_votes":3694,"rep_votes":4608,"other_votes":419,"total_votes":8721,"dem_candidate":"Al Gore","rep_candidate":"George W. Bush","margin":914,"margin_pct":10.480449,"winner":"REPUBLICAN","color":"#ef3b2c"},{"county":"Washington","dem_votes":49637,"rep_votes":51502,"other_votes":5164,"total_votes":106303,"dem_candidate":"Al Gore","rep_candidate":"George W. Bush","margin":1865,"margin_pct":1.754419,"winner":"REPUBLICAN","color":"#fcae91"},{"county":"Watonwan","dem_votes":2258,"rep_votes":2562,"other_votes":222,"total_votes":5042,"dem_candidate":"Al Gore","rep_candidate":"George W. Bush","margin":304,"margin_pct":6.029353,"winner":"REPUBLICAN","color":"#fb6a4a"},{"county":"Wilkin","dem_votes":1046,"rep_votes":2032,"other_votes":89,"total_votes":3167,"dem_candidate":"Al Gore","rep_candidate":"George W. Bush","margin":986,"margin_pct":31.133565,"winner":"REPUBLICAN","color":"#a50f15"},{"county":"Winona","dem_votes":11069,"rep_votes":10773,"other_votes":1837,"total_votes":23679,"dem_candidate":"Al Gore","rep_candidate":"George W. Bush","margin":-296,"margin_pct":-1.250053,"winner":"DEMOCRAT","color":"#c6dbef"},{"county":"Wright","dem_votes":16762,"rep_votes":23861,"other_votes":2112,"total_votes":42735,"dem_candidate":"Al Gore","rep_candidate":"George W. Bush","margin":7099,"margin_pct":16.611677,"winner":"REPUBLICAN","color":"#ef3b2c"},{"county":"Yellow Medicine","dem_votes":2528,"rep_votes":2598,"other_votes":243,"total_votes":5369,"dem_candidate":"Al Gore","rep_candidate":"George W. Bush","margin":70,"margin_pct":1.303781,"winner":"REPUBLICAN","color":"#fcae91"}],"meta":{"source_file":"20001107__mn__general__county.csv","generated_at_utc":"2026-03-15T05:22:13Z"}}