{"contest_type":"secretary_of_state","year":2018,"state":"MN","rows":[{"county":"Aitkin","dem_votes":3177,"rep_votes":4467,"other_votes":350,"total_votes":7994,"dem_candidate":"Steve Simon","rep_candidate":"John Howe","margin":1290,"margin_pct":16.137103,"winner":"REPUBLICAN","color":"#ef3b2c"},{"county":"Anoka","dem_votes":72853,"rep_votes":76044,"other_votes":7188,"total_votes":156085,"dem_candidate":"Steve Simon","rep_candidate":"John Howe","margin":3191,"margin_pct":2.044399,"winner":"REPUBLICAN","color":"#fcae91"},{"county":"Becker","dem_votes":5380,"rep_votes":8462,"other_votes":570,"total_votes":14412,"dem_candidate":"Steve Simon","rep_candidate":"John Howe","margin":3082,"margin_pct":21.384957,"winner":"REPUBLICAN","color":"#cb181d"},{"county":"Beltrami","dem_votes":8634,"rep_votes":8494,"other_votes":596,"total_votes":17724,"dem_candidate":"Steve Simon","rep_candidate":"John Howe","margin":-140,"margin_pct":-0.789889,"winner":"DEMOCRAT","color":"#e1f5fe"},{"county":"Benton","dem_votes":5676,"rep_votes":9384,"other_votes":773,"total_votes":15833,"dem_candidate":"Steve Simon","rep_candidate":"John Howe","margin":3708,"margin_pct":23.41944,"winner":"REPUBLICAN","color":"#cb181d"},{"county":"Big Stone","dem_votes":1022,"rep_votes":1421,"other_votes":103,"total_votes":2546,"dem_candidate":"Steve Simon","rep_candidate":"John Howe","margin":399,"margin_pct":15.671642,"winner":"REPUBLICAN","color":"#ef3b2c"},{"county":"Blue Earth","dem_votes":14275,"rep_votes":11824,"other_votes":1440,"total_votes":27539,"dem_candidate":"Steve Simon","rep_candidate":"John Howe","margin":-2451,"margin_pct":-8.900105,"winner":"DEMOCRAT","color":"#9ecae1"},{"county":"Brown","dem_votes":4048,"rep_votes":6927,"other_votes":601,"total_votes":11576,"dem_candidate":"Steve Simon","rep_candidate":"John Howe","margin":2879,"margin_pct":24.870422,"winner":"REPUBLICAN","color":"#cb181d"},{"county":"Carlton","dem_votes":8782,"rep_votes":6577,"other_votes":625,"total_votes":15984,"dem_candidate":"Steve Simon","rep_candidate":"John Howe","margin":-2205,"margin_pct":-13.795045,"winner":"DEMOCRAT","color":"#6baed6"},{"county":"Carver","dem_votes":20658,"rep_votes":27054,"other_votes":1985,"total_votes":49697,"dem_candidate":"Steve Simon","rep_candidate":"John Howe","margin":6396,"margin_pct":12.869992,"winner":"REPUBLICAN","color":"#ef3b2c"},{"county":"Cass","dem_votes":5060,"rep_votes":8320,"other_votes":448,"total_votes":13828,"dem_candidate":"Steve Simon","rep_candidate":"John Howe","margin":3260,"margin_pct":23.575354,"winner":"REPUBLICAN","color":"#cb181d"},{"county":"Chippewa","dem_votes":2125,"rep_votes":3000,"other_votes":234,"total_votes":5359,"dem_candidate":"Steve Simon","rep_candidate":"John Howe","margin":875,"margin_pct":16.327673,"winner":"REPUBLICAN","color":"#ef3b2c"},{"county":"Chisago","dem_votes":9666,"rep_votes":14622,"other_votes":1068,"total_votes":25356,"dem_candidate":"Steve Simon","rep_candidate":"John Howe","margin":4956,"margin_pct":19.54567,"winner":"REPUBLICAN","color":"#ef3b2c"},{"county":"Clay","dem_votes":12526,"rep_votes":10246,"other_votes":992,"total_votes":23764,"dem_candidate":"Steve Simon","rep_candidate":"John Howe","margin":-2280,"margin_pct":-9.594344,"winner":"DEMOCRAT","color":"#9ecae1"},{"county":"Clearwater","dem_votes":1107,"rep_votes":2220,"other_votes":107,"total_votes":3434,"dem_candidate":"Steve Simon","rep_candidate":"John Howe","margin":1113,"margin_pct":32.411182,"winner":"REPUBLICAN","color":"#a50f15"},{"county":"Cook","dem_votes":1970,"rep_votes":1013,"other_votes":138,"total_votes":3121,"dem_candidate":"Steve Simon","rep_candidate":"John Howe","margin":-957,"margin_pct":-30.663249,"winner":"DEMOCRAT","color":"#08519c"},{"county":"Cottonwood","dem_votes":1797,"rep_votes":2948,"other_votes":200,"total_votes":4945,"dem_candidate":"Steve Simon","rep_candidate":"John Howe","margin":1151,"margin_pct":23.276036,"winner":"REPUBLICAN","color":"#cb181d"},{"county":"Crow Wing","dem_votes":11230,"rep_votes":18373,"other_votes":1169,"total_votes":30772,"dem_candidate":"Steve Simon","rep_candidate":"John Howe","margin":7143,"margin_pct":23.212661,"winner":"REPUBLICAN","color":"#cb181d"},{"county":"Dakota","dem_votes":106904,"rep_votes":88729,"other_votes":8438,"total_votes":204071,"dem_candidate":"Steve Simon","rep_candidate":"John Howe","margin":-18175,"margin_pct":-8.906214,"winner":"DEMOCRAT","color":"#9ecae1"},{"county":"Dodge","dem_votes":3219,"rep_votes":5219,"other_votes":461,"total_votes":8899,"dem_candidate":"Steve Simon","rep_candidate":"John Howe","margin":2000,"margin_pct":22.474435,"winner":"REPUBLICAN","color":"#cb181d"},{"county":"Douglas","dem_votes":6207,"rep_votes":10900,"other_votes":646,"total_votes":17753,"dem_candidate":"Steve Simon","rep_candidate":"John Howe","margin":4693,"margin_pct":26.434969,"winner":"REPUBLICAN","color":"#cb181d"},{"county":"Faribault","dem_votes":2196,"rep_votes":3720,"other_votes":362,"total_votes":6278,"dem_candidate":"Steve Simon","rep_candidate":"John Howe","margin":1524,"margin_pct":24.275247,"winner":"REPUBLICAN","color":"#cb181d"},{"county":"Fillmore","dem_votes":3922,"rep_votes":5147,"other_votes":425,"total_votes":9494,"dem_candidate":"Steve Simon","rep_candidate":"John Howe","margin":1225,"margin_pct":12.902886,"winner":"REPUBLICAN","color":"#ef3b2c"},{"county":"Freeborn","dem_votes":6113,"rep_votes":6952,"other_votes":643,"total_votes":13708,"dem_candidate":"Steve Simon","rep_candidate":"John Howe","margin":839,"margin_pct":6.120514,"winner":"REPUBLICAN","color":"#fb6a4a"},{"county":"Goodhue","dem_votes":9475,"rep_votes":12289,"other_votes":1015,"total_votes":22779,"dem_candidate":"Steve Simon","rep_candidate":"John Howe","margin":2814,"margin_pct":12.353483,"winner":"REPUBLICAN","color":"#ef3b2c"},{"county":"Grant","dem_votes":1232,"rep_votes":1684,"other_votes":164,"total_votes":3080,"dem_candidate":"Steve Simon","rep_candidate":"John Howe","margin":452,"margin_pct":14.675325,"winner":"REPUBLICAN","color":"#ef3b2c"},{"county":"Hennepin","dem_votes":410681,"rep_votes":181839,"other_votes":23403,"total_votes":615923,"dem_candidate":"Steve Simon","rep_candidate":"John Howe","margin":-228842,"margin_pct":-37.15432,"winner":"DEMOCRAT","color":"#08519c"},{"county":"Houston","dem_votes":3954,"rep_votes":4534,"other_votes":306,"total_votes":8794,"dem_candidate":"Steve Simon","rep_candidate":"John Howe","margin":580,"margin_pct":6.595406,"winner":"REPUBLICAN","color":"#fb6a4a"},{"county":"Hubbard","dem_votes":3663,"rep_votes":6039,"other_votes":325,"total_votes":10027,"dem_candidate":"Steve Simon","rep_candidate":"John Howe","margin":2376,"margin_pct":23.696021,"winner":"REPUBLICAN","color":"#cb181d"},{"county":"Isanti","dem_votes":5812,"rep_votes":10538,"other_votes":716,"total_votes":17066,"dem_candidate":"Steve Simon","rep_candidate":"John Howe","margin":4726,"margin_pct":27.692488,"winner":"REPUBLICAN","color":"#cb181d"},{"county":"Itasca","dem_votes":9768,"rep_votes":10607,"other_votes":851,"total_votes":21226,"dem_candidate":"Steve Simon","rep_candidate":"John Howe","margin":839,"margin_pct":3.9527,"winner":"REPUBLICAN","color":"#fcae91"},{"county":"Jackson","dem_votes":1684,"rep_votes":2704,"other_votes":228,"total_votes":4616,"dem_candidate":"Steve Simon","rep_candidate":"John Howe","margin":1020,"margin_pct":22.097054,"winner":"REPUBLICAN","color":"#cb181d"},{"county":"Kanabec","dem_votes":2449,"rep_votes":3875,"other_votes":290,"total_votes":6614,"dem_candidate":"Steve Simon","rep_candidate":"John Howe","margin":1426,"margin_pct":21.560327,"winner":"REPUBLICAN","color":"#cb181d"},{"county":"Kandiyohi","dem_votes":7124,"rep_votes":10461,"other_votes":756,"total_votes":18341,"dem_candidate":"Steve Simon","rep_candidate":"John Howe","margin":3337,"margin_pct":18.19421,"winner":"REPUBLICAN","color":"#ef3b2c"},{"county":"Kittson","dem_votes":1084,"rep_votes":1118,"other_votes":76,"total_votes":2278,"dem_candidate":"Steve Simon","rep_candidate":"John Howe","margin":34,"margin_pct":1.492537,"winner":"REPUBLICAN","color":"#fcae91"},{"county":"Koochiching","dem_votes":2494,"rep_votes":2526,"other_votes":151,"total_votes":5171,"dem_candidate":"Steve Simon","rep_candidate":"John Howe","margin":32,"margin_pct":0.618836,"winner":"REPUBLICAN","color":"#fee8c8"},{"county":"Lac Qui Parle","dem_votes":1397,"rep_votes":1758,"other_votes":146,"total_votes":3301,"dem_candidate":"Steve Simon","rep_candidate":"John Howe","margin":361,"margin_pct":10.93608,"winner":"REPUBLICAN","color":"#ef3b2c"},{"county":"Lake","dem_votes":3183,"rep_votes":2472,"other_votes":191,"total_votes":5846,"dem_candidate":"Steve Simon","rep_candidate":"John Howe","margin":-711,"margin_pct":-12.162162,"winner":"DEMOCRAT","color":"#6baed6"},{"county":"Lake Of The Woods","dem_votes":601,"rep_votes":1162,"other_votes":67,"total_votes":1830,"dem_candidate":"Steve Simon","rep_candidate":"John Howe","margin":561,"margin_pct":30.655738,"winner":"REPUBLICAN","color":"#a50f15"},{"county":"Le Sueur","dem_votes":4827,"rep_votes":7109,"other_votes":623,"total_votes":12559,"dem_candidate":"Steve Simon","rep_candidate":"John Howe","margin":2282,"margin_pct":18.170236,"winner":"REPUBLICAN","color":"#ef3b2c"},{"county":"Lincoln","dem_votes":943,"rep_votes":1344,"other_votes":115,"total_votes":2402,"dem_candidate":"Steve Simon","rep_candidate":"John Howe","margin":401,"margin_pct":16.694421,"winner":"REPUBLICAN","color":"#ef3b2c"},{"county":"Lyon","dem_votes":3808,"rep_votes":5573,"other_votes":433,"total_votes":9814,"dem_candidate":"Steve Simon","rep_candidate":"John Howe","margin":1765,"margin_pct":17.984512,"winner":"REPUBLICAN","color":"#ef3b2c"},{"county":"Mahnomen","dem_votes":1024,"rep_votes":782,"other_votes":85,"total_votes":1891,"dem_candidate":"Steve Simon","rep_candidate":"John Howe","margin":-242,"margin_pct":-12.797462,"winner":"DEMOCRAT","color":"#6baed6"},{"county":"Marshall","dem_votes":1416,"rep_votes":2479,"other_votes":114,"total_votes":4009,"dem_candidate":"Steve Simon","rep_candidate":"John Howe","margin":1063,"margin_pct":26.51534,"winner":"REPUBLICAN","color":"#cb181d"},{"county":"Martin","dem_votes":2727,"rep_votes":5424,"other_votes":441,"total_votes":8592,"dem_candidate":"Steve Simon","rep_candidate":"John Howe","margin":2697,"margin_pct":31.389665,"winner":"REPUBLICAN","color":"#a50f15"},{"county":"Mcleod","dem_votes":4808,"rep_votes":9264,"other_votes":674,"total_votes":14746,"dem_candidate":"Steve Simon","rep_candidate":"John Howe","margin":4456,"margin_pct":30.218364,"winner":"REPUBLICAN","color":"#a50f15"},{"county":"Meeker","dem_votes":3349,"rep_votes":6419,"other_votes":418,"total_votes":10186,"dem_candidate":"Steve Simon","rep_candidate":"John Howe","margin":3070,"margin_pct":30.139407,"winner":"REPUBLICAN","color":"#a50f15"},{"county":"Mille Lacs","dem_votes":3716,"rep_votes":6277,"other_votes":438,"total_votes":10431,"dem_candidate":"Steve Simon","rep_candidate":"John Howe","margin":2561,"margin_pct":24.551817,"winner":"REPUBLICAN","color":"#cb181d"},{"county":"Morrison","dem_votes":3905,"rep_votes":9628,"other_votes":461,"total_votes":13994,"dem_candidate":"Steve Simon","rep_candidate":"John Howe","margin":5723,"margin_pct":40.896098,"winner":"REPUBLICAN","color":"#67000d"},{"county":"Mower","dem_votes":7076,"rep_votes":6670,"other_votes":661,"total_votes":14407,"dem_candidate":"Steve Simon","rep_candidate":"John Howe","margin":-406,"margin_pct":-2.818075,"winner":"DEMOCRAT","color":"#c6dbef"},{"county":"Murray","dem_votes":1523,"rep_votes":2358,"other_votes":158,"total_votes":4039,"dem_candidate":"Steve Simon","rep_candidate":"John Howe","margin":835,"margin_pct":20.673434,"winner":"REPUBLICAN","color":"#cb181d"},{"county":"Nicollet","dem_votes":7883,"rep_votes":6670,"other_votes":863,"total_votes":15416,"dem_candidate":"Steve Simon","rep_candidate":"John Howe","margin":-1213,"margin_pct":-7.868448,"winner":"DEMOCRAT","color":"#9ecae1"},{"county":"Nobles","dem_votes":2735,"rep_votes":3803,"other_votes":291,"total_votes":6829,"dem_candidate":"Steve Simon","rep_candidate":"John Howe","margin":1068,"margin_pct":15.639186,"winner":"REPUBLICAN","color":"#ef3b2c"},{"county":"Norman","dem_votes":1278,"rep_votes":1242,"other_votes":130,"total_votes":2650,"dem_candidate":"Steve Simon","rep_candidate":"John Howe","margin":-36,"margin_pct":-1.358491,"winner":"DEMOCRAT","color":"#c6dbef"},{"county":"Olmsted","dem_votes":34894,"rep_votes":31848,"other_votes":3009,"total_votes":69751,"dem_candidate":"Steve Simon","rep_candidate":"John Howe","margin":-3046,"margin_pct":-4.366962,"winner":"DEMOCRAT","color":"#c6dbef"},{"county":"Otter Tail","dem_votes":9526,"rep_votes":16593,"other_votes":894,"total_votes":27013,"dem_candidate":"Steve Simon","rep_candidate":"John Howe","margin":7067,"margin_pct":26.161478,"winner":"REPUBLICAN","color":"#cb181d"},{"county":"Pennington","dem_votes":2157,"rep_votes":2916,"other_votes":230,"total_votes":5303,"dem_candidate":"Steve Simon","rep_candidate":"John Howe","margin":759,"margin_pct":14.312653,"winner":"REPUBLICAN","color":"#ef3b2c"},{"county":"Pine","dem_votes":4635,"rep_votes":6289,"other_votes":497,"total_votes":11421,"dem_candidate":"Steve Simon","rep_candidate":"John Howe","margin":1654,"margin_pct":14.482094,"winner":"REPUBLICAN","color":"#ef3b2c"},{"county":"Pipestone","dem_votes":1111,"rep_votes":2420,"other_votes":144,"total_votes":3675,"dem_candidate":"Steve Simon","rep_candidate":"John Howe","margin":1309,"margin_pct":35.619048,"winner":"REPUBLICAN","color":"#a50f15"},{"county":"Polk","dem_votes":4580,"rep_votes":6619,"other_votes":414,"total_votes":11613,"dem_candidate":"Steve Simon","rep_candidate":"John Howe","margin":2039,"margin_pct":17.557909,"winner":"REPUBLICAN","color":"#ef3b2c"},{"county":"Pope","dem_votes":2174,"rep_votes":2982,"other_votes":225,"total_votes":5381,"dem_candidate":"Steve Simon","rep_candidate":"John Howe","margin":808,"margin_pct":15.015796,"winner":"REPUBLICAN","color":"#ef3b2c"},{"county":"Ramsey","dem_votes":165949,"rep_votes":63364,"other_votes":10358,"total_votes":239671,"dem_candidate":"Steve Simon","rep_candidate":"John Howe","margin":-102585,"margin_pct":-42.802425,"winner":"DEMOCRAT","color":"#08306b"},{"county":"Red Lake","dem_votes":716,"rep_votes":819,"other_votes":77,"total_votes":1612,"dem_candidate":"Steve Simon","rep_candidate":"John Howe","margin":103,"margin_pct":6.389578,"winner":"REPUBLICAN","color":"#fb6a4a"},{"county":"Redwood","dem_votes":1922,"rep_votes":3933,"other_votes":265,"total_votes":6120,"dem_candidate":"Steve Simon","rep_candidate":"John Howe","margin":2011,"margin_pct":32.859477,"winner":"REPUBLICAN","color":"#a50f15"},{"county":"Renville","dem_votes":2274,"rep_votes":3639,"other_votes":290,"total_votes":6203,"dem_candidate":"Steve Simon","rep_candidate":"John Howe","margin":1365,"margin_pct":22.005481,"winner":"REPUBLICAN","color":"#cb181d"},{"county":"Rice","dem_votes":14162,"rep_votes":12452,"other_votes":1214,"total_votes":27828,"dem_candidate":"Steve Simon","rep_candidate":"John Howe","margin":-1710,"margin_pct":-6.14489,"winner":"DEMOCRAT","color":"#9ecae1"},{"county":"Rock","dem_votes":1228,"rep_votes":2343,"other_votes":144,"total_votes":3715,"dem_candidate":"Steve Simon","rep_candidate":"John Howe","margin":1115,"margin_pct":30.013459,"winner":"REPUBLICAN","color":"#a50f15"},{"county":"Roseau","dem_votes":1925,"rep_votes":4280,"other_votes":175,"total_votes":6380,"dem_candidate":"Steve Simon","rep_candidate":"John Howe","margin":2355,"margin_pct":36.912226,"winner":"REPUBLICAN","color":"#a50f15"},{"county":"Scott","dem_votes":27671,"rep_votes":34600,"other_votes":2805,"total_votes":65076,"dem_candidate":"Steve Simon","rep_candidate":"John Howe","margin":6929,"margin_pct":10.647551,"winner":"REPUBLICAN","color":"#ef3b2c"},{"county":"Sherburne","dem_votes":13098,"rep_votes":23957,"other_votes":1677,"total_votes":38732,"dem_candidate":"Steve Simon","rep_candidate":"John Howe","margin":10859,"margin_pct":28.036249,"winner":"REPUBLICAN","color":"#cb181d"},{"county":"Sibley","dem_votes":2078,"rep_votes":4028,"other_votes":336,"total_votes":6442,"dem_candidate":"Steve Simon","rep_candidate":"John Howe","margin":1950,"margin_pct":30.270102,"winner":"REPUBLICAN","color":"#a50f15"},{"county":"St. Louis","dem_votes":58261,"rep_votes":35069,"other_votes":3655,"total_votes":96985,"dem_candidate":"Steve Simon","rep_candidate":"John Howe","margin":-23192,"margin_pct":-23.912976,"winner":"DEMOCRAT","color":"#3182bd"},{"county":"Stearns","dem_votes":24897,"rep_votes":37682,"other_votes":2510,"total_votes":65089,"dem_candidate":"Steve Simon","rep_candidate":"John Howe","margin":12785,"margin_pct":19.642336,"winner":"REPUBLICAN","color":"#ef3b2c"},{"county":"Steele","dem_votes":6236,"rep_votes":9019,"other_votes":765,"total_votes":16020,"dem_candidate":"Steve Simon","rep_candidate":"John Howe","margin":2783,"margin_pct":17.372035,"winner":"REPUBLICAN","color":"#ef3b2c"},{"county":"Stevens","dem_votes":1744,"rep_votes":2339,"other_votes":160,"total_votes":4243,"dem_candidate":"Steve Simon","rep_candidate":"John Howe","margin":595,"margin_pct":14.023097,"winner":"REPUBLICAN","color":"#ef3b2c"},{"county":"Swift","dem_votes":1678,"rep_votes":2131,"other_votes":170,"total_votes":3979,"dem_candidate":"Steve Simon","rep_candidate":"John Howe","margin":453,"margin_pct":11.38477,"winner":"REPUBLICAN","color":"#ef3b2c"},{"county":"Todd","dem_votes":2856,"rep_votes":6249,"other_votes":357,"total_votes":9462,"dem_candidate":"Steve Simon","rep_candidate":"John Howe","margin":3393,"margin_pct":35.859226,"winner":"REPUBLICAN","color":"#a50f15"},{"county":"Traverse","dem_votes":611,"rep_votes":816,"other_votes":66,"total_votes":1493,"dem_candidate":"Steve Simon","rep_candidate":"John Howe","margin":205,"margin_pct":13.730743,"winner":"REPUBLICAN","color":"#ef3b2c"},{"county":"Wabasha","dem_votes":3781,"rep_votes":5527,"other_votes":474,"total_votes":9782,"dem_candidate":"Steve Simon","rep_candidate":"John Howe","margin":1746,"margin_pct":17.849111,"winner":"REPUBLICAN","color":"#ef3b2c"},{"county":"Wadena","dem_votes":1606,"rep_votes":3688,"other_votes":171,"total_votes":5465,"dem_candidate":"Steve Simon","rep_candidate":"John Howe","margin":2082,"margin_pct":38.096981,"winner":"REPUBLICAN","color":"#a50f15"},{"county":"Waseca","dem_votes":2935,"rep_votes":4611,"other_votes":430,"total_votes":7976,"dem_candidate":"Steve Simon","rep_candidate":"John Howe","margin":1676,"margin_pct":21.013039,"winner":"REPUBLICAN","color":"#cb181d"},{"county":"Washington","dem_votes":64401,"rep_votes":57900,"other_votes":5201,"total_votes":127502,"dem_candidate":"Steve Simon","rep_candidate":"John Howe","margin":-6501,"margin_pct":-5.098744,"winner":"DEMOCRAT","color":"#c6dbef"},{"county":"Watonwan","dem_votes":1685,"rep_votes":2197,"other_votes":191,"total_votes":4073,"dem_candidate":"Steve Simon","rep_candidate":"John Howe","margin":512,"margin_pct":12.570587,"winner":"REPUBLICAN","color":"#ef3b2c"},{"county":"Wilkin","dem_votes":908,"rep_votes":1503,"other_votes":119,"total_votes":2530,"dem_candidate":"Steve Simon","rep_candidate":"John Howe","margin":595,"margin_pct":23.517787,"winner":"REPUBLICAN","color":"#cb181d"},{"county":"Winona","dem_votes":10910,"rep_votes":9200,"other_votes":887,"total_votes":20997,"dem_candidate":"Steve Simon","rep_candidate":"John Howe","margin":-1710,"margin_pct":-8.144021,"winner":"DEMOCRAT","color":"#9ecae1"},{"county":"Wright","dem_votes":20132,"rep_votes":34854,"other_votes":2702,"total_votes":57688,"dem_candidate":"Steve Simon","rep_candidate":"John Howe","margin":14722,"margin_pct":25.520039,"winner":"REPUBLICAN","color":"#cb181d"},{"county":"Yellow Medicine","dem_votes":1595,"rep_votes":2515,"other_votes":163,"total_votes":4273,"dem_candidate":"Steve Simon","rep_candidate":"John Howe","margin":920,"margin_pct":21.530541,"winner":"REPUBLICAN","color":"#cb181d"}],"meta":{"source_file":"20181106__mn__general__county.csv","generated_at_utc":"2026-03-15T05:22:13Z"}}